siat/__init__.py
siat/allin.py
siat/assets_liquidity.py
siat/beta_adjustment.py
siat/beta_adjustment_china.py
siat/blockchain.py
siat/bond.py
siat/bond_base.py
siat/bond_china.py
siat/bond_zh_sina.py
siat/cache.py
siat/cache_init.py
siat/capm_beta.py
siat/capm_beta2.py
siat/common.py
siat/compare_cross.py
siat/copyrights.py
siat/cryptocurrency.py
siat/economy.py
siat/economy2-20251209.py
siat/economy2.py
siat/economy3.py
siat/esg.py
siat/event_study.py
siat/exchange_bond_china.pickle
siat/fama_french.py
siat/fama_french2.py
siat/fin_stmt2_yahoo.py
siat/financial_base.py
siat/financial_statements.py
siat/financials.py
siat/financials2.py
siat/financials_china-20251121.py
siat/financials_china.py
siat/financials_china2.py
siat/fund.py
siat/fund_china.pickle
siat/fund_china.py
siat/future_china.py
siat/google_authenticator.py
siat/grafix.py
siat/grafix2.py
siat/grafix2_20260112.py
siat/holding_risk.py
siat/luchy_draw.py
siat/market_china.py
siat/markowitz.py
siat/markowitz2.py
siat/markowitz3.py
siat/markowitz4.py
siat/ml_cases.py
siat/ml_cases_example.py
siat/option_china.py
siat/option_greek_demo1.py
siat/option_greek_demo2.py
siat/option_pricing.py
siat/other_indexes.py
siat/pdf_process.py
siat/quantitative1.py
siat/quantitative2.py
siat/risk_adjusted_return.py
siat/risk_adjusted_return2.py
siat/risk_adjusted_return3.py
siat/risk_evaluation.py
siat/risk_free_rate.py
siat/save2docx.py
siat/save2pdf.py
siat/sector_china.py
siat/security_price2.py
siat/security_prices.py
siat/security_trend.py
siat/security_trend2.py
siat/security_trend3.py
siat/stock.py
siat/stock_advice_linear.py
siat/stock_base.py
siat/stock_china.py
siat/stock_info.pickle
siat/stock_prices_kneighbors.py
siat/stock_prices_linear.py
siat/stock_profile.py
siat/stock_technical.py
siat/stock_technical2.py
siat/stooq.py
siat/transaction.py
siat/translate.py
siat/valuation.py
siat/valuation_china.py
siat/var_model_validation.py
siat/yf_name.py
siat-3.33.31.dist-info/licenses/LICENSE
siat-3.33.31.dist-info/METADATA
siat-3.33.31.dist-info/WHEEL
siat-3.33.31.dist-info/top_level.txt
siat-3.33.31.dist-info/RECORD
