Metadata-Version: 2.4
Name: siat
Version: 3.33.31
Summary: Securities Investment Analysis Tools (siat)
Author-email: "Prof. WANG Dehong (Peter), copyright, all rights reserved" <wdehong2000@163.com>
Maintainer-email: "Prof. WANG Dehong (Peter)" <wdehong2000@163.com>
License-Expression: MIT
Project-URL: Homepage, https://pypi.org/project/siat/
Keywords: securities,investment,analysis,case study,siat
Requires-Python: <3.13,>=3.9
License-File: LICENSE
Requires-Dist: pandas_datareader
Requires-Dist: yfinance
Requires-Dist: tqdm
Requires-Dist: plotly_express
Requires-Dist: akshare
Requires-Dist: urllib3
Requires-Dist: mplfinance
Requires-Dist: statsmodels
Requires-Dist: yahoo_earnings_calendar
Requires-Dist: pypinyin
Requires-Dist: seaborn
Requires-Dist: scipy
Requires-Dist: pandas
Requires-Dist: scikit-learn
Requires-Dist: baostock
Requires-Dist: ruamel-yaml
Requires-Dist: prettytable
Requires-Dist: graphviz
Requires-Dist: luddite
Requires-Dist: pendulum
Requires-Dist: itables
Requires-Dist: py_trans
Requires-Dist: bottleneck
Requires-Dist: translate
Requires-Dist: translators
Requires-Dist: nbconvert
Requires-Dist: ipywidgets==8.1.6
Requires-Dist: yahooquery==2.3.7
Requires-Dist: alpha_vantage
Requires-Dist: tiingo[pandas]
Requires-Dist: numpy<2
Requires-Dist: playwright
Requires-Dist: pymupdf
Requires-Dist: pypandoc
Requires-Dist: python-docx
Requires-Dist: weasyprint
Requires-Dist: pandas_market_calendars
Requires-Dist: pypdf
Requires-Dist: pdf2docx
Requires-Dist: lxml
Requires-Dist: markdown
Requires-Dist: docutils<0.22,>=0.18.1
Requires-Dist: requests_cache
Requires-Dist: TA-Lib
Requires-Dist: requests_cache
Requires-Dist: pykalman
Dynamic: license-file
